linpymem/__init__.py
linpymem/core.py
tests/integration_test.py
linpymem-0.4.0.dist-info/LICENSE
linpymem-0.4.0.dist-info/METADATA
linpymem-0.4.0.dist-info/WHEEL
linpymem-0.4.0.dist-info/top_level.txt
linpymem-0.4.0.dist-info/RECORD
