Metadata-Version: 2.1
Name: linpymem
Version: 0.4.0
Summary: Low-level physical memory access via Linpmem kernel driver
Author-email: gionetti <its.only.a.matter.of.time.000@gmail.com>
License: MIT
Project-URL: Homepage, https://github.com/gionetti/linpymem
Requires-Python: >=3.7
License-File: LICENSE
Requires-Dist: psutil
